{
  "generator-jhipster": {
    "promptValues": {
      "packageName": "org.chafraterno",
      "nativeLanguage": "pt-br"
    },
    "jhipsterVersion": "4.10.2",
    "baseName": "chafraterno",
    "packageName": "org.chafraterno",
    "packageFolder": "org/chafraterno",
    "serverPort": "8080",
    "authenticationType": "jwt",
    "hibernateCache": "ehcache",
    "clusteredHttpSession": false,
    "websocket": false,
    "databaseType": "sql",
    "devDatabaseType": "h2Disk",
    "prodDatabaseType": "postgresql",
    "searchEngine": false,
    "messageBroker": false,
    "serviceDiscoveryType": false,
    "buildTool": "maven",
    "enableSocialSignIn": true,
    "enableSwaggerCodegen": false,
    "jwtSecretKey": "cd0b129425dfee0a0292a1215972d6b753bafa01",
    "clientFramework": "angularX",
    "useSass": false,
    "clientPackageManager": "yarn",
    "applicationType": "monolith",
    "testFrameworks": [
      "cucumber"
    ],
    "jhiPrefix": "jhi",
    "otherModules": [
      {
        "name": "generator-jhipster-bootstrap-material-design",
        "version": "3.5.1"
      }
    ],
    "enableTranslation": true,
    "nativeLanguage": "pt-br",
    "languages": [
      "pt-br"
    ]
  }
}